.codecov.yml
.codedocs
.gitignore
.travis.yml
CMakeLists.txt
Doxyfile.in
MANIFEST.in
README.md
VERSION
appveyor.yml
coverity_model.c
env.yml
logo.png
setup.py
uploadpypi.sh
.git/HEAD
.git/config
.git/description
.git/index
.git/packed-refs
.git/hooks/applypatch-msg.sample
.git/hooks/commit-msg.sample
.git/hooks/fsmonitor-watchman.sample
.git/hooks/post-update.sample
.git/hooks/pre-applypatch.sample
.git/hooks/pre-commit.sample
.git/hooks/pre-merge-commit.sample
.git/hooks/pre-push.sample
.git/hooks/pre-rebase.sample
.git/hooks/pre-receive.sample
.git/hooks/prepare-commit-msg.sample
.git/hooks/push-to-checkout.sample
.git/hooks/update.sample
.git/info/exclude
.git/logs/HEAD
.git/logs/refs/heads/manifest-fix
.git/logs/refs/heads/master
.git/logs/refs/remotes/origin/HEAD
.git/objects/pack/pack-2d5584e55d26fe12b69d5daa4cedc10f7c9eef35.idx
.git/objects/pack/pack-2d5584e55d26fe12b69d5daa4cedc10f7c9eef35.pack
.git/refs/heads/manifest-fix
.git/refs/heads/master
.git/refs/remotes/origin/HEAD
.github/workflows/ccpp.yml
JASSv1/CI.c
JASSv1/CI.h
JASSv1/GNUmakefile
JASSv1/atire_to_jass_index.c
JASSv1/compress.h
JASSv1/compress_integer_elias_delta_simd.c
JASSv1/compress_integer_elias_delta_simd.h
JASSv1/compress_integer_elias_gamma_simd.c
JASSv1/compress_integer_elias_gamma_simd.h
JASSv1/compress_integer_elias_gamma_simd_vb.cpp
JASSv1/compress_integer_elias_gamma_simd_vb.h
JASSv1/compress_integer_variable_byte.cpp
JASSv1/compress_integer_variable_byte.h
JASSv1/compress_qmx.c
JASSv1/compress_qmx.h
JASSv1/compress_qmx_d4.c
JASSv1/compress_qmx_d4.h
JASSv1/compress_qmx_decompress.c
JASSv1/compress_simple8b.c
JASSv1/compress_simple8b.h
JASSv1/compress_variable_byte.c
JASSv1/compress_variable_byte.h
JASSv1/forceinline.h
JASSv1/heap.h
JASSv1/jass.c
JASSv1/maths.c
JASSv1/maths.h
JASSv1/process_postings.c
JASSv1/process_postings.h
JASSv1/data/queries.clueweb09.txt
JASSv1/data/queries.clueweb12.txt
JASSv1/data/queries.gov2.txt
JASSv1/data/topics.terabyte.701-750.txt
jassTest.egg-info/PKG-INFO
jassTest.egg-info/SOURCES.txt
jassTest.egg-info/dependency_links.txt
jassTest.egg-info/top_level.txt
