Metadata-Version: 2.1
Name: jassTest
Version: 2.0.2
Summary: Some short description about the stuff goes here
Home-page: UNKNOWN
Author: Pradeesh P
Author-email: andrew@cs.otago.ac.nz
License: UNKNOWN
Project-URL: Bug Reports, https://github.com/andrewtrotman/JASSv2/issues
Project-URL: Source, https://github.com/andrewtrotman/JASSv2
Keywords: search engine,search tool,jass
Platform: UNKNOWN
Classifier: Programming Language :: Python :: 3
Classifier: Operating System :: MacOS :: MacOS X
Classifier: Operating System :: POSIX :: Linux
Requires-Python: >=3.0
